agenet/__init__.py
agenet/aaoi.py
agenet/blkerr.py
agenet/cli.py
agenet/simulation.py
agenet/snratio.py
agenet-1.0.0.dist-info/LICENSE
agenet-1.0.0.dist-info/METADATA
agenet-1.0.0.dist-info/WHEEL
agenet-1.0.0.dist-info/entry_points.txt
agenet-1.0.0.dist-info/top_level.txt
agenet-1.0.0.dist-info/RECORD
