Metadata-Version: 2.1
Name: agenet
Version: 1.0.0
Summary: Age of Information Model for wireless networks
Author-email: Chathuranga Basanayaka <chathurangab@sltc.ac.lk>, Nuno Fachada <nuno.fachada@ulusofona.pt>
License: MIT
Project-URL: Homepage, https://github.com/cahthuranag/agenet
Project-URL: Bug Reports, https://github.com/cahthuranag/agenet/issues
Project-URL: Documentation, https://cahthuranag.github.io/agenet/
Keywords: age of information ,URLLC,age of information model,AoI
Classifier: License :: OSI Approved :: MIT License
Classifier: Operating System :: OS Independent
Classifier: Programming Language :: Python
Classifier: Intended Audience :: Science/Research
Classifier: Topic :: Scientific/Engineering
Requires-Python: >=3.9
License-File: LICENSE
Requires-Dist: matplotlib
Requires-Dist: numpy
Requires-Dist: pandas
Requires-Dist: rich
Requires-Dist: rich-argparse
Requires-Dist: rich-tools
Requires-Dist: scipy
Provides-Extra: dev
Requires-Dist: pytest ; extra == 'dev'
Requires-Dist: pytest-cov ; extra == 'dev'
Requires-Dist: pytest-console-scripts ; extra == 'dev'
Requires-Dist: pytest-mock ; extra == 'dev'
Requires-Dist: coverage ; extra == 'dev'
Requires-Dist: codecov ; extra == 'dev'
Requires-Dist: mypy ; extra == 'dev'
Requires-Dist: pytest-mypy ; extra == 'dev'
Requires-Dist: mkdocs-material >=7.1.11 ; extra == 'dev'
Requires-Dist: mkdocstrings[python] >=0.19.0 ; extra == 'dev'
Requires-Dist: black ; extra == 'dev'
Requires-Dist: flake8 >=6.0.0 ; extra == 'dev'
Requires-Dist: flake8-black ; extra == 'dev'
Requires-Dist: flake8-builtins ; extra == 'dev'
Requires-Dist: flake8-comprehensions ; extra == 'dev'
Requires-Dist: flake8-docstrings ; extra == 'dev'
Requires-Dist: flake8-isort ; extra == 'dev'
Requires-Dist: Flake8-pyproject ; extra == 'dev'
Requires-Dist: flake8-pytest-style ; extra == 'dev'
Requires-Dist: flake8-simplify ; extra == 'dev'
Requires-Dist: isort ; extra == 'dev'
Requires-Dist: pre-commit ; extra == 'dev'
Requires-Dist: typing ; extra == 'dev'
